{
    "gameTime": 529.833,
    "goalsData": [
        {
            "goalScorerName": "MaddoHatto",
            "goalShotTime": 23.717,
            "goalSide": "Blue",
            "goalSpeed": 3.421,
            "goalTime": 24.45,
            "goalTravelTime": 0.733
        },
        {
            "goalScorerName": "Amman",
            "goalShotTime": 76.617,
            "goalSide": "Blue",
            "goalSpeed": 4.63,
            "goalTime": 77.183,
            "goalTravelTime": 0.566
        },
        {
            "goalScorerName": "MaddoHatto",
            "goalShotTime": 84.633,
            "goalSide": "Blue",
            "goalSpeed": 1.933,
            "goalTime": 86.3,
            "goalTravelTime": 1.667
        },
        {
            "goalScorerName": "ToPP",
            "goalShotTime": 216.067,
            "goalSide": "Red",
            "goalSpeed": 2.884,
            "goalTime": 216.417,
            "goalTravelTime": 0.35
        },
        {
            "goalScorerName": "MaddoHatto",
            "goalShotTime": 233.283,
            "goalSide": "Blue",
            "goalSpeed": 1.4,
            "goalTime": 234.7,
            "goalTravelTime": 1.417
        },
        {
            "goalScorerName": "Amman",
            "goalShotTime": 264.533,
            "goalSide": "Blue",
            "goalSpeed": 1.382,
            "goalTime": 266.617,
            "goalTravelTime": 2.084
        },
        {
            "goalScorerName": "hubigz",
            "goalShotTime": 270.733,
            "goalSide": "Red",
            "goalSpeed": 3.688,
            "goalTime": 271.233,
            "goalTravelTime": 0.5
        },
        {
            "goalScorerName": "MaddoHatto",
            "goalShotTime": 279.4,
            "goalSide": "Blue",
            "goalSpeed": 3.858,
            "goalTime": 279.733,
            "goalTravelTime": 0.333
        },
        {
            "goalScorerName": "Amman",
            "goalShotTime": 389.25,
            "goalSide": "Blue",
            "goalSpeed": 3.415,
            "goalTime": 390.35,
            "goalTravelTime": 1.1
        },
        {
            "goalScorerName": "MaddoHatto",
            "goalShotTime": 436.6,
            "goalSide": "Blue",
            "goalSpeed": 4.83,
            "goalTime": 437.733,
            "goalTravelTime": 1.133
        },
        {
            "goalScorerName": "MaddoHatto",
            "goalShotTime": 470.1,
            "goalSide": "Blue",
            "goalSpeed": 2.118,
            "goalTime": 472.0,
            "goalTravelTime": 1.9
        },
        {
            "goalScorerName": "ToPP",
            "goalShotTime": 476.033,
            "goalSide": "Red",
            "goalSpeed": 2.846,
            "goalTime": 477.05,
            "goalTravelTime": 1.017
        },
        {
            "goalScorerName": "hubigz",
            "goalShotTime": 484.567,
            "goalSide": "Red",
            "goalSpeed": 2.471,
            "goalTime": 486.85,
            "goalTravelTime": 2.283
        },
        {
            "goalScorerName": "Amman",
            "goalShotTime": 527.15,
            "goalSide": "Blue",
            "goalSpeed": 3.238,
            "goalTime": 529.833,
            "goalTravelTime": 2.683
        }
    ],
    "rawPositionsAtEnd": "-293.6672104224639--5.251854461340443|-405.0--58.129212854023805|-162.02771627771878-48.54555467617554|-324.30293732201466-16.66534455321597|",
    "score": {
        "Blue": 10,
        "Red": 4
    },
    "startingGameTime": 0,
    "teams": {
        "Blue": [
            "MaddoHatto",
            "Amman"
        ],
        "Red": [
            "hubigz",
            "ToPP"
        ]
    },
    "time": "2021-09-03 10:30"
}