{
    "gameTime": 539.417,
    "goalsData": [
        {
            "goalScorerName": "hubigz",
            "goalShotTime": 9.333,
            "goalSide": "Blue",
            "goalSpeed": 5.298,
            "goalTime": 9.617,
            "goalTravelTime": 0.284
        },
        {
            "goalScorerName": "Nelson Mandela",
            "goalShotTime": 16.733,
            "goalSide": "Blue",
            "goalSpeed": 5.271,
            "goalTime": 17.017,
            "goalTravelTime": 0.284
        },
        {
            "goalScorerName": "ToPP",
            "goalShotTime": 51.633,
            "goalSide": "Red",
            "goalSpeed": 5.67,
            "goalTime": 52.567,
            "goalTravelTime": 0.934
        },
        {
            "goalScorerName": "ToPP",
            "goalShotTime": 60.417,
            "goalSide": "Red",
            "goalSpeed": 8.527,
            "goalTime": 60.583,
            "goalTravelTime": 0.166
        },
        {
            "goalScorerName": "Nelson Mandela",
            "goalShotTime": 124.733,
            "goalSide": "Blue",
            "goalSpeed": 1.819,
            "goalTime": 126.617,
            "goalTravelTime": 1.884
        },
        {
            "goalScorerName": "ToPP",
            "goalShotTime": 173.483,
            "goalSide": "Red",
            "goalSpeed": 6.095,
            "goalTime": 173.583,
            "goalTravelTime": 0.1
        },
        {
            "goalScorerName": "ToPP",
            "goalShotTime": 264.633,
            "goalSide": "Red",
            "goalSpeed": 0.958,
            "goalTime": 266.233,
            "goalTravelTime": 1.6
        },
        {
            "goalScorerName": "ToPP",
            "goalShotTime": 274.183,
            "goalSide": "Red",
            "goalSpeed": 1.463,
            "goalTime": 276.583,
            "goalTravelTime": 2.4
        },
        {
            "goalScorerName": "ToPP",
            "goalShotTime": 320.933,
            "goalSide": "Red",
            "goalSpeed": 2.719,
            "goalTime": 322.05,
            "goalTravelTime": 1.117
        },
        {
            "goalScorerName": "ToPP",
            "goalShotTime": 328.533,
            "goalSide": "Red",
            "goalSpeed": 5.723,
            "goalTime": 331.633,
            "goalTravelTime": 3.1
        },
        {
            "goalScorerName": "Nelson Mandela",
            "goalShotTime": 377.217,
            "goalSide": "Blue",
            "goalSpeed": 5.45,
            "goalTime": 379.617,
            "goalTravelTime": 2.4
        },
        {
            "goalScorerName": "ToPP",
            "goalShotTime": 419.783,
            "goalSide": "Red",
            "goalSpeed": 1.822,
            "goalTime": 420.2,
            "goalTravelTime": 0.417
        },
        {
            "goalScorerName": "Nelson Mandela",
            "goalShotTime": 422.167,
            "goalSide": "Blue",
            "goalSpeed": 4.647,
            "goalTime": 422.767,
            "goalTravelTime": 0.6
        },
        {
            "goalScorerName": "hubigz",
            "goalShotTime": 456.483,
            "goalSide": "Blue",
            "goalSpeed": 6.192,
            "goalTime": 456.583,
            "goalTravelTime": 0.1
        },
        {
            "goalScorerName": "MaddoHatto",
            "goalShotTime": 505.283,
            "goalSide": "Red",
            "goalSpeed": 5.715,
            "goalTime": 505.567,
            "goalTravelTime": 0.284
        },
        {
            "goalScorerName": "Nelson Mandela",
            "goalShotTime": 523.583,
            "goalSide": "Blue",
            "goalSpeed": 4.368,
            "goalTime": 523.917,
            "goalTravelTime": 0.334
        },
        {
            "goalScorerName": "ToPP",
            "goalShotTime": 539.333,
            "goalSide": "Red",
            "goalSpeed": 1.706,
            "goalTime": 539.417,
            "goalTravelTime": 0.084
        }
    ],
    "rawPositionsAtEnd": "286.05133200092547--9.516615994254703|345.601734472132-38.924432748294585|318.77593449177573--29.42862575034846|365.07984964042714--96.20586380230591|",
    "score": {
        "Blue": 7,
        "Red": 10
    },
    "startingGameTime": 0,
    "teams": {
        "Blue": [
            "hubigz",
            "Nelson Mandela"
        ],
        "Red": [
            "MaddoHatto",
            "ToPP"
        ]
    },
    "time": "2021-08-19 15:25"
}